lpaas_client/__init__.py
lpaas_client/asyn/__init__.py
lpaas_client/asyn/async_client.py
lpaas_client/asyn/routes/__init__.py
lpaas_client/asyn/routes/auth.py
lpaas_client/asyn/routes/goals.py
lpaas_client/asyn/routes/solutions.py
lpaas_client/asyn/routes/theories.py
lpaas_client/core/__init__.py
lpaas_client/core/client/__init__.py
lpaas_client/core/client/baseclient.py
lpaas_client/core/exception/__init__.py
lpaas_client/core/exception/exception.py
lpaas_client/core/model/__init__.py
lpaas_client/core/model/auth.py
lpaas_client/core/model/goal.py
lpaas_client/core/model/solution.py
lpaas_client/core/model/theory.py
lpaas_client/core/routes/__init__.py
lpaas_client/core/routes/authBaseRoute.py
lpaas_client/core/routes/goalBaseRoute.py
lpaas_client/core/routes/solutionBaseRoute.py
lpaas_client/core/routes/theoryBaseRoute.py
lpaas_client/serializer/__init__.py
lpaas_client/serializer/serializer.py
lpaas_client/sync/__init__.py
lpaas_client/sync/sync_client.py
lpaas_client/sync/routes/__init__.py
lpaas_client/sync/routes/auth.py
lpaas_client/sync/routes/goals.py
lpaas_client/sync/routes/solutions.py
lpaas_client/sync/routes/theories.py
tests/asyn/__init__.py
tests/asyn/routes/__init__.py
tests/asyn/routes/test_auth.py
tests/asyn/routes/test_goals.py
tests/asyn/routes/test_solutions.py
tests/asyn/routes/test_theories.py
tests/core/__init__.py
tests/core/model/__init__.py
tests/core/model/test_goals.py
tests/core/model/test_theory.py
tests/serializer/__init__.py
tests/serializer/test_serializer.py
tests/serializer/utils.py
tests/sync/__init__.py
tests/sync/test_sync_client.py
tests/sync/routes/__init__.py
tests/sync/routes/test_auth.py
tests/sync/routes/test_goals.py
tests/sync/routes/test_solutions.py
tests/sync/routes/test_theories.py
lpaas_client-0.5.3.dist-info/LICENSE
lpaas_client-0.5.3.dist-info/METADATA
lpaas_client-0.5.3.dist-info/WHEEL
lpaas_client-0.5.3.dist-info/top_level.txt
lpaas_client-0.5.3.dist-info/RECORD
