Metadata-Version: 2.1
Name: lpaas-client
Version: 0.5.3
Summary: Python implementation of a client for LPaaS
Home-page: https://gitlab.com/pika-lab/courses/ds/projects/ds-project-evangelisti-ay2021
Author: Davide Evangelisti
Author-email: davide.evangelisti2@studio.unibo.it
License: Apache 2.0 License
Project-URL: Bug Reports, https://gitlab.com/pika-lab/courses/ds/projects/ds-project-evangelisti-ay2021/-/issues
Project-URL: Source, https://gitlab.com/pika-lab/courses/ds/projects/ds-project-evangelisti-ay2021/-/tree/main/lpaas-client
Keywords: prolog,client,tuprolog,2p,python,lpaas
Platform: Independent
Classifier: Development Status :: 2 - Pre-Alpha
Classifier: Intended Audience :: Developers
Classifier: Topic :: Software Development :: Libraries
Classifier: License :: OSI Approved :: Apache Software License
Classifier: Programming Language :: Python :: 3
Classifier: Programming Language :: Python :: 3.7
Classifier: Programming Language :: Python :: 3.8
Classifier: Programming Language :: Python :: 3.9
Classifier: Programming Language :: Python :: 3 :: Only
Classifier: Programming Language :: Prolog
Requires-Python: >=3.7, <4
License-File: LICENSE
Requires-Dist: 2ppy (==0.4.0)
Requires-Dist: httpx (~=0.21.1)
Requires-Dist: http-constants (~=0.5)
Requires-Dist: dataclasses (~=0.6)
Requires-Dist: isodate (~=0.6)
